Metadata-Version: 2.1
Name: urllib3
Version: 1.26.1
Summary: HTTP library with thread-safe connection pooling, file post, and more.
Home-page: https://urllib3.readthedocs.io/
Author: Andrey Petrov
Author-email: andrey.petrov@shazow.net
License: MIT
Project-URL: Documentation, https://urllib3.readthedocs.io/
Project-URL: Code, https://github.com/urllib3/urllib3
Project-URL: Issue tracker, https://github.com/urllib3/urllib3/issues
Keywords: urllib httplib threadsafe filepost http https ssl pooling
Platform: UNKNOWN
Classifier: Environment :: Web Environment
Classifier: Intended Audience :: Developers
Classifier: License :: OSI Approved :: MIT License
Classifier: Operating System :: OS Independent
Classifier: Programming Language :: Python
Classifier: Programming Language :: Python :: 2
Classifier: Programming Language :: Python :: 2.7
Classifier: Programming Language :: Python :: 3
Classifier: Programming Language :: Python :: 3.5
Classifier: Programming Language :: Python :: 3.6
Classifier: Programming Language :: Python :: 3.7
Classifier: Programming Language :: Python :: 3.8
Classifier: Programming Language :: Python :: 3.9
Classifier: Programming Language :: Python :: Implementation :: CPython
Classifier: Programming Language :: Python :: Implementation :: PyPy
Classifier: Topic :: Internet :: WWW/HTTP
Classifier: Topic :: Software Development :: Libraries
Requires-Python: >=2.7, !=3.0.*, !=3.1.*, !=3.2.*, !=3.3.*, !=3.4.*, <4
Provides-Extra: brotli
Provides-Extra: secure
Provides-Extra: socks
